README.rst
setup.py
html2rml/__init__.py
html2rml.egg-info/PKG-INFO
html2rml.egg-info/SOURCES.txt
html2rml.egg-info/dependency_links.txt
html2rml.egg-info/top_level.txt
html2rml/templatetags/__init__.py
html2rml/templatetags/html2rml.py