Metadata-Version: 1.1
Name: html2rml
Version: 0.3.1
Summary: Simple HTML to RML converter
Home-page: https://github.com/misli/html2rml
Author: Jakub Dorňák
Author-email: jakub.dornak@misli.cz
License: BSD
Platform: UNKNOWN
Classifier: Development Status :: 3 - Alpha
Classifier: Environment :: Web Environment
Classifier: Intended Audience :: Developers
Classifier: License :: OSI Approved :: BSD License
Classifier: Operating System :: OS Independent
Classifier: Programming Language :: Python
Classifier: Programming Language :: Python :: 3.9
Classifier: Programming Language :: Python :: 3.8
Classifier: Programming Language :: Python :: 3.7
Classifier: Programming Language :: Python :: 3.6
Classifier: Programming Language :: Python :: 2.7
